{
    "msisdn":"6285717483267" ,
    "fname":"Santanu" ,
    "lname":"Paul" ,
    "refNo":"MTX77664433" ,
    "segment":"Prepaid",
    "serviceClass":"SC 637 IM3 SP 0 Cashback 90d" ,
    "idtype":"Driving Licence" ,
    "idRef":"34458719" ,
    "idExp":"2023-06-03" ,
    "address":"172/3 Sector V , Webel more , Kolkata",
    "city":"Jakarta",
    "cluster": "High-High Value Sophisticated",
    "indi":"Treatment" ,
    "clusterColor" : "green",
    "puk1":"95453759" ,
    "puk2":"347687876" ,
    "iccid":"895645342787977" ,
    "imei":"861536030196001" ,
    "poc":"ABCD" ,
    "firstActive":"2022-05-30",
    "bal":"5674521" ,
    "activationDate":"2022-05-31" ,
    "grace":"30",
    "accnState":"Active",

    "activePacks":[{
    "pid":"ULNEW200KFS" ,
    "name":"Fredom Internet 150GB,200rb" ,
    "start":"2022-04-30" ,
    "end":"2022-06-30" 
    }],

    "packageHist":[{
    "pid":"ULNEW200KFS" ,
    "name":"Fredom Internet 150GB,200rb" ,
    "start":"2022-04-30" ,
    "end":"2022-06-30"
    }],

    "activities":[{
    "no": "1-2IVJLP",
    "title":"",
    "type":"Inbound Call",
    "intType":"SR" ,
    "reason":"SIM Card",
    "status":"Completed" 
    }] ,
    "orders":[{
    "orderno": "1-TYPL22U",
    "ordertype":"Modify Prepiad",
    "orderStatus":"Submitted",
    "orderDate":"2022-06-01" ,
    "orderRemark":"VIP to Non VIP"
    },
    {
    "orderno": "1-V34KH5G",
    "ordertype":"New Registration",
    "orderStatus":"Completed",
    "orderDate":"2020-01-30" ,
    "orderRemark":""
    }] ,
    

    "camData":"1 GB",
    "camSMS": "250",
    "camVoice":"Unlimited",
    "camMix":"" ,
    "rbtTitle":"NA",
    "rbtStatus":"Inactive",
    "subDate":"" 
 }